{
	"response": [
		{
			"maintainer": "erwinabs",
			"oem": "Xiaomi",
			"device": "Poco F4",
			"filename": "RisingOS-3.1-RELEASE-20240521-CORE-OFFICIAL-munch-ota.zip",
			"download": "https://sourceforge.net/projects/risingos-official/files/3.x/CORE/munch/RisingOS-3.1-RELEASE-20240521-CORE-OFFICIAL-munch-ota.zip/download",
			"timestamp": 1716319963,
			"md5": "d97621408c0e4fa46ea97814b7301136",
			"sha256": "bc6bf459495dd32e4b9a73af53e2957b3061066d8afabe68a72a3ed65c6ef9f5",
			"size": 2181614566,
			"version": "3.1-Janus",
			"buildtype": "RELEASE",
			"forum": "https://t.me/namanyajugarom",
			"gapps": "",
			"firmware": "",
			"modem": "",
			"bootloader": "",
			"recovery": "",
			"paypal": "https://linktr.ee/erwinabs",
			"telegram": "https://t.me/erwinabs",
			"dt": "",
			"common-dt": "",
			"kernel": ""
		}
	]
}
